pipeserial
