Metadata-Version: 2.1
Name: pipeserial
Version: 0.2.0
Summary: PipeSerial is a command-line utility to send some input from stdin to a serial device, and then collect and return the output from the device.
Home-page: https://github.com/tykling/pipeserial
Author: Thomas Steen Rasmussen
Author-email: thomas@gibfest.dk
License: BSD License
Platform: UNKNOWN
Classifier: Programming Language :: Python :: 3.7
Classifier: Programming Language :: Python :: 3.8
Classifier: License :: OSI Approved :: BSD License
Classifier: Operating System :: OS Independent
Requires-Python: >=3.7
